tufa/__init__.py
tufa/__main__.py
tufa/cli.py
tufa/commands.py
tufa/exceptions.py
tufa/metadata.py
tufa/operations.py
tufa/otp.py
tufa/secrets.py
tufa/validation.py
tufa-0.2.0.dist-info/LICENSE
tufa-0.2.0.dist-info/METADATA
tufa-0.2.0.dist-info/WHEEL
tufa-0.2.0.dist-info/entry_points.txt
tufa-0.2.0.dist-info/top_level.txt
tufa-0.2.0.dist-info/RECORD
