Metadata-Version: 2.1
Name: tufa
Version: 0.2.0
Summary: A command-line tool for managing TOTP/HOTP credentials using the Mac OS keychain.
Home-page: https://github.com/nickgaya/tufa
Author: Nicholas Gaya
Author-email: nicholasgaya+pypi@gmail.com
License: UNKNOWN
Project-URL: Bug Tracker, https://github.com/nickgaya/tufa/issues
Platform: UNKNOWN
Classifier: Development Status :: 4 - Beta
Classifier: Environment :: Console
Classifier: Intended Audience :: End Users/Desktop
Classifier: License :: OSI Approved :: MIT License
Classifier: Operating System :: MacOS :: MacOS X
Classifier: Programming Language :: Python :: 3
Classifier: Topic :: Security
Requires-Python: ~=3.7
License-File: LICENSE
